<?xml version="1.1" encoding="UTF-8"?>

<xwikidoc version="1.4" reference="XWiki.Carousel.CarouselTemplate" locale="">
  <web>XWiki.Carousel</web>
  <name>CarouselTemplate</name>
  <language/>
  <defaultLanguage/>
  <translation>0</translation>
  <creator>xwiki:XWiki.Admin</creator>
  <parent>WebHome</parent>
  <author>xwiki:XWiki.Admin</author>
  <contentAuthor>xwiki:XWiki.Admin</contentAuthor>
  <version>1.1</version>
  <title/>
  <comment/>
  <minorEdit>false</minorEdit>
  <syntaxId>xwiki/2.1</syntaxId>
  <hidden>true</hidden>
  <content/>
  <object>
    <name>XWiki.Carousel.CarouselTemplate</name>
    <number>0</number>
    <className>XWiki.Carousel.CarouselClass</className>
    <guid>84f3a2bd-1427-484a-9c7d-c321f8e4771f</guid>
    <class>
      <name>XWiki.Carousel.CarouselClass</name>
      <customClass/>
      <customMapping/>
      <defaultViewSheet/>
      <defaultEditSheet/>
      <defaultWeb/>
      <nameField/>
      <validationScript/>
      <bgcolor>
        <customDisplay/>
        <disabled>0</disabled>
        <hint/>
        <name>bgcolor</name>
        <number>2</number>
        <picker>0</picker>
        <prettyName>bgcolor</prettyName>
        <size>30</size>
        <unmodifiable>0</unmodifiable>
        <validationMessage/>
        <validationRegExp/>
        <classType>com.xpn.xwiki.objects.classes.StringClass</classType>
      </bgcolor>
      <color>
        <customDisplay/>
        <disabled>0</disabled>
        <hint/>
        <name>color</name>
        <number>2</number>
        <picker>1</picker>
        <prettyName>color</prettyName>
        <size>30</size>
        <unmodifiable>0</unmodifiable>
        <validationMessage/>
        <validationRegExp/>
        <classType>com.xpn.xwiki.objects.classes.StringClass</classType>
      </color>
    </class>
    <property>
      <bgcolor/>
    </property>
    <property>
      <color/>
    </property>
  </object>
</xwikidoc>
